.gitignore
.travis.yml
CHANGES.rst
LICENSE.txt
README.rst
bootstrap.py
buildout.cfg
setup.py
tox.ini
js/__init__.py
js.leaflet.egg-info/PKG-INFO
js.leaflet.egg-info/SOURCES.txt
js.leaflet.egg-info/dependency_links.txt
js.leaflet.egg-info/entry_points.txt
js.leaflet.egg-info/namespace_packages.txt
js.leaflet.egg-info/not-zip-safe
js.leaflet.egg-info/requires.txt
js.leaflet.egg-info/top_level.txt
js/leaflet/__init__.py
js/leaflet/test_leaflet.txt
js/leaflet/resources/leaflet-src.js
js/leaflet/resources/leaflet.css
js/leaflet/resources/leaflet.ie.css
js/leaflet/resources/leaflet.ie.min.css
js/leaflet/resources/leaflet.js
js/leaflet/resources/leaflet.min.css
js/leaflet/resources/images/layers-2x.png
js/leaflet/resources/images/layers.png
js/leaflet/resources/images/marker-icon-2x.png
js/leaflet/resources/images/marker-icon.png
js/leaflet/resources/images/marker-icon@2x.png
js/leaflet/resources/images/marker-shadow.png
js/leaflet/resources/images/zoom-in.png
js/leaflet/resources/images/zoom-out.png