Metadata-Version: 1.0
Name: js.leaflet
Version: 0.6.2
Summary: Fanstatic packaging of Leaflet
Home-page: https://github.com/davidjb/js.leaflet
Author: Fanstatic Developers
Author-email: fanstatic@googlegroups.com
License: BSD
Keywords: javascript mapping map leaflet js openlayers
Platform: UNKNOWN
